k8s_agent/__init__.py
k8s_agent/__main__.py
k8s_agent/cli.py
k8s_agent/config.py
k8s_agent/http.py
k8s_agent/commands/__init__.py
k8s_agent/commands/auth.py
k8s_agent/commands/vm.py
k8s_agent-0.3.0.dist-info/licenses/LICENSE
k8s_agent-0.3.0.dist-info/METADATA
k8s_agent-0.3.0.dist-info/WHEEL
k8s_agent-0.3.0.dist-info/entry_points.txt
k8s_agent-0.3.0.dist-info/top_level.txt
k8s_agent-0.3.0.dist-info/RECORD
