Metadata-Version: 2.4
Name: k8s-agent
Version: 0.3.0
Summary: CLI tool for K8sVMGr - Kubernetes VM Manager
Author-email: Chenxu Fu <fuchenxu1997@gmail.com>
License-Expression: MIT
Project-URL: Homepage, https://github.com/fuchenxu/k8s-agent
Project-URL: Documentation, https://github.com/fuchenxu/k8s-agent#readme
Project-URL: Repository, https://github.com/fuchenxu/k8s-agent
Project-URL: Bug Tracker, https://github.com/fuchenxu/k8s-agent/issues
Keywords: kubernetes,vm,cli,k8s,management
Classifier: Development Status :: 4 - Beta
Classifier: Intended Audience :: Developers
Classifier: Intended Audience :: System Administrators
Classifier: Programming Language :: Python :: 3
Classifier: Programming Language :: Python :: 3.8
Classifier: Programming Language :: Python :: 3.9
Classifier: Programming Language :: Python :: 3.10
Classifier: Programming Language :: Python :: 3.11
Classifier: Programming Language :: Python :: 3.12
Classifier: Topic :: System :: Systems Administration
Classifier: Topic :: Utilities
Requires-Python: >=3.8
License-File: LICENSE
Requires-Dist: click>=7.0
Requires-Dist: requests>=2.28.0
Provides-Extra: dev
Requires-Dist: pytest>=7.0; extra == "dev"
Requires-Dist: black>=22.0; extra == "dev"
Requires-Dist: mypy>=1.0; extra == "dev"
Dynamic: license-file
